package com.facebook.common.references;

import com.facebook.common.internal.Closeables;
import com.facebook.common.internal.Preconditions;
import com.facebook.common.internal.VisibleForTesting;
import com.facebook.common.logging.FLog;
import com.facebook.infer.annotation.PropagatesNullable;
import java.io.Closeable;
import java.io.IOException;
import java.util.ArrayList;
import java.util.Collection;
import java.util.Iterator;
import java.util.List;
import javax.annotation.Nullable;
import javax.annotation.concurrent.GuardedBy;

public final class CloseableReference<T>
  implements Cloneable, Closeable
{
  private static final ResourceReleaser<Closeable> DEFAULT_CLOSEABLE_RELEASER = new ResourceReleaser()
  {
    public void release(Closeable paramAnonymousCloseable)
    {
      try
      {
        Closeables.close(paramAnonymousCloseable, true);
        return;
      }
      catch (IOException paramAnonymousCloseable) {}
    }
  };
  private static final LeakHandler DEFAULT_LEAK_HANDLER = new LeakHandler()
  {
    public void reportLeak(SharedReference<Object> paramAnonymousSharedReference, @Nullable Throwable paramAnonymousThrowable)
    {
      FLog.w(CloseableReference.TAG, "Finalized without closing: %x %x (type = %s)", new Object[] { Integer.valueOf(System.identityHashCode(this)), Integer.valueOf(System.identityHashCode(paramAnonymousSharedReference)), paramAnonymousSharedReference.get().getClass().getName() });
    }
    
    public boolean requiresStacktrace()
    {
      return false;
    }
  };
  private static Class<CloseableReference> TAG = CloseableReference.class;
  @GuardedBy("this")
  private boolean mIsClosed = false;
  private final LeakHandler mLeakHandler;
  private final SharedReference<T> mSharedReference;
  @Nullable
  private final Throwable mStacktrace;
  
  private CloseableReference(SharedReference<T> paramSharedReference, LeakHandler paramLeakHandler, @Nullable Throwable paramThrowable)
  {
    mSharedReference = ((SharedReference)Preconditions.checkNotNull(paramSharedReference));
    paramSharedReference.addReference();
    mLeakHandler = paramLeakHandler;
    mStacktrace = paramThrowable;
  }
  
  private CloseableReference(T paramT, ResourceReleaser<T> paramResourceReleaser, LeakHandler paramLeakHandler, @Nullable Throwable paramThrowable)
  {
    mSharedReference = new SharedReference(paramT, paramResourceReleaser);
    mLeakHandler = paramLeakHandler;
    mStacktrace = paramThrowable;
  }
  
  @Nullable
  public static <T> CloseableReference<T> cloneOrNull(@Nullable CloseableReference<T> paramCloseableReference)
  {
    if (paramCloseableReference != null) {
      return paramCloseableReference.cloneOrNull();
    }
    return null;
  }
  
  public static <T> List<CloseableReference<T>> cloneOrNull(@PropagatesNullable Collection<CloseableReference<T>> paramCollection)
  {
    if (paramCollection == null) {
      return null;
    }
    ArrayList localArrayList = new ArrayList(paramCollection.size());
    paramCollection = paramCollection.iterator();
    while (paramCollection.hasNext()) {
      localArrayList.add(cloneOrNull((CloseableReference)paramCollection.next()));
    }
    return localArrayList;
  }
  
  public static void closeSafely(@Nullable CloseableReference<?> paramCloseableReference)
  {
    if (paramCloseableReference != null) {
      paramCloseableReference.close();
    }
  }
  
  public static void closeSafely(@Nullable Iterable<? extends CloseableReference<?>> paramIterable)
  {
    if (paramIterable != null)
    {
      paramIterable = paramIterable.iterator();
      while (paramIterable.hasNext()) {
        closeSafely((CloseableReference)paramIterable.next());
      }
    }
  }
  
  public static boolean isValid(@Nullable CloseableReference<?> paramCloseableReference)
  {
    return (paramCloseableReference != null) && (paramCloseableReference.isValid());
  }
  
  public static <T extends Closeable> CloseableReference<T> of(@PropagatesNullable T paramT)
  {
    return of(paramT, DEFAULT_CLOSEABLE_RELEASER);
  }
  
  public static <T extends Closeable> CloseableReference<T> of(@PropagatesNullable T paramT, LeakHandler paramLeakHandler)
  {
    Throwable localThrowable = null;
    if (paramT == null) {
      return null;
    }
    ResourceReleaser localResourceReleaser = DEFAULT_CLOSEABLE_RELEASER;
    if (paramLeakHandler.requiresStacktrace()) {
      localThrowable = new Throwable();
    }
    return new CloseableReference(paramT, localResourceReleaser, paramLeakHandler, localThrowable);
  }
  
  public static <T> CloseableReference<T> of(@PropagatesNullable T paramT, ResourceReleaser<T> paramResourceReleaser)
  {
    return of(paramT, paramResourceReleaser, DEFAULT_LEAK_HANDLER);
  }
  
  public static <T> CloseableReference<T> of(@PropagatesNullable T paramT, ResourceReleaser<T> paramResourceReleaser, LeakHandler paramLeakHandler)
  {
    Throwable localThrowable = null;
    if (paramT == null) {
      return null;
    }
    if (paramLeakHandler.requiresStacktrace()) {
      localThrowable = new Throwable();
    }
    return new CloseableReference(paramT, paramResourceReleaser, paramLeakHandler, localThrowable);
  }
  
  public CloseableReference<T> clone()
  {
    try
    {
      Preconditions.checkState(isValid());
      CloseableReference localCloseableReference = new CloseableReference(mSharedReference, mLeakHandler, mStacktrace);
      return localCloseableReference;
    }
    finally
    {
      localObject = finally;
      throw localObject;
    }
  }
  
  @Nullable
  public CloseableReference<T> cloneOrNull()
  {
    try
    {
      if (isValid())
      {
        CloseableReference localCloseableReference = clone();
        return localCloseableReference;
      }
      return null;
    }
    finally
    {
      localObject = finally;
      throw localObject;
    }
  }
  
  public void close()
  {
    try
    {
      if (mIsClosed) {
        return;
      }
      mIsClosed = true;
      mSharedReference.deleteReference();
      return;
    }
    finally {}
  }
  
  /* Error */
  protected void finalize()
    throws Throwable
  {
    // Byte code:
    //   0: aload_0
    //   1: monitorenter
    //   2: aload_0
    //   3: getfield 53	com/facebook/common/references/CloseableReference:mIsClosed	Z
    //   6: ifeq +10 -> 16
    //   9: aload_0
    //   10: monitorexit
    //   11: aload_0
    //   12: invokespecial 182	java/lang/Object:finalize	()V
    //   15: return
    //   16: aload_0
    //   17: monitorexit
    //   18: aload_0
    //   19: getfield 68	com/facebook/common/references/CloseableReference:mLeakHandler	Lcom/facebook/common/references/CloseableReference$LeakHandler;
    //   22: aload_0
    //   23: getfield 63	com/facebook/common/references/CloseableReference:mSharedReference	Lcom/facebook/common/references/SharedReference;
    //   26: aload_0
    //   27: getfield 70	com/facebook/common/references/CloseableReference:mStacktrace	Ljava/lang/Throwable;
    //   30: invokeinterface 186 3 0
    //   35: aload_0
    //   36: invokevirtual 129	com/facebook/common/references/CloseableReference:close	()V
    //   39: aload_0
    //   40: invokespecial 182	java/lang/Object:finalize	()V
    //   43: return
    //   44: astore_1
    //   45: aload_0
    //   46: monitorexit
    //   47: aload_1
    //   48: athrow
    //   49: astore_1
    //   50: aload_0
    //   51: invokespecial 182	java/lang/Object:finalize	()V
    //   54: aload_1
    //   55: athrow
    // Local variable table:
    //   start	length	slot	name	signature
    //   0	56	0	this	CloseableReference
    //   44	4	1	localObject1	Object
    //   49	6	1	localObject2	Object
    // Exception table:
    //   from	to	target	type
    //   2	11	44	finally
    //   16	18	44	finally
    //   45	47	44	finally
    //   0	2	49	finally
    //   18	39	49	finally
    //   47	49	49	finally
  }
  
  public T get()
  {
    try
    {
      Preconditions.checkState(mIsClosed ^ true);
      Object localObject1 = mSharedReference.get();
      return localObject1;
    }
    finally
    {
      localObject2 = finally;
      throw localObject2;
    }
  }
  
  @VisibleForTesting
  public SharedReference<T> getUnderlyingReferenceTestOnly()
  {
    try
    {
      SharedReference localSharedReference = mSharedReference;
      return localSharedReference;
    }
    finally
    {
      localObject = finally;
      throw localObject;
    }
  }
  
  public int getValueHash()
  {
    if (isValid()) {
      return System.identityHashCode(mSharedReference.get());
    }
    return 0;
  }
  
  public boolean isValid()
  {
    try
    {
      boolean bool = mIsClosed;
      return bool ^ true;
    }
    finally
    {
      localObject = finally;
      throw localObject;
    }
  }
  
  public static abstract interface LeakHandler
  {
    public abstract void reportLeak(SharedReference<Object> paramSharedReference, @Nullable Throwable paramThrowable);
    
    public abstract boolean requiresStacktrace();
  }
}
