package androidx.room;

import android.annotation.SuppressLint;
import android.app.ActivityManager;
import android.content.Context;
import android.database.Cursor;
import android.os.Build.VERSION;
import android.os.Looper;
import android.util.Log;
import androidx.annotation.CallSuper;
import androidx.annotation.NonNull;
import androidx.annotation.Nullable;
import androidx.annotation.RequiresApi;
import androidx.annotation.RestrictTo;
import androidx.annotation.WorkerThread;
import androidx.arch.core.executor.ArchTaskExecutor;
import androidx.collection.SparseArrayCompat;
import androidx.core.app.ActivityManagerCompat;
import androidx.room.migration.Migration;
import androidx.sqlite.db.SimpleSQLiteQuery;
import androidx.sqlite.db.SupportSQLiteDatabase;
import androidx.sqlite.db.SupportSQLiteOpenHelper;
import androidx.sqlite.db.SupportSQLiteOpenHelper.Factory;
import androidx.sqlite.db.SupportSQLiteQuery;
import androidx.sqlite.db.SupportSQLiteStatement;
import androidx.sqlite.db.framework.FrameworkSQLiteOpenHelperFactory;
import java.util.ArrayList;
import java.util.Collections;
import java.util.HashSet;
import java.util.Iterator;
import java.util.List;
import java.util.Map;
import java.util.Set;
import java.util.concurrent.ConcurrentHashMap;
import java.util.concurrent.Executor;
import java.util.concurrent.locks.Lock;
import java.util.concurrent.locks.ReentrantReadWriteLock;
import java.util.concurrent.locks.ReentrantReadWriteLock.WriteLock;

public abstract class RoomDatabase
{
  private static final String DB_IMPL_SUFFIX = "_Impl";
  @RestrictTo({androidx.annotation.RestrictTo.Scope.LIBRARY_GROUP_PREFIX})
  public static final int MAX_BIND_PARAMETER_CNT = 999;
  private boolean mAllowMainThreadQueries;
  private final Map<String, Object> mBackingFieldMap = new ConcurrentHashMap();
  @Deprecated
  @Nullable
  protected List<Callback> mCallbacks;
  private final ReentrantReadWriteLock mCloseLock = new ReentrantReadWriteLock();
  @Deprecated
  protected volatile SupportSQLiteDatabase mDatabase;
  private final InvalidationTracker mInvalidationTracker = createInvalidationTracker();
  private SupportSQLiteOpenHelper mOpenHelper;
  private Executor mQueryExecutor;
  private final ThreadLocal<Integer> mSuspendingTransactionId = new ThreadLocal();
  private Executor mTransactionExecutor;
  boolean mWriteAheadLoggingEnabled;
  
  public RoomDatabase() {}
  
  private static boolean isMainThread()
  {
    return Looper.getMainLooper().getThread() == Thread.currentThread();
  }
  
  @RestrictTo({androidx.annotation.RestrictTo.Scope.LIBRARY_GROUP_PREFIX})
  public void assertNotMainThread()
  {
    if (mAllowMainThreadQueries) {
      return;
    }
    if (!isMainThread()) {
      return;
    }
    throw new IllegalStateException("Cannot access database on the main thread since it may potentially lock the UI for a long period of time.");
  }
  
  @RestrictTo({androidx.annotation.RestrictTo.Scope.LIBRARY_GROUP})
  public void assertNotSuspendingTransaction()
  {
    if (!inTransaction())
    {
      if (mSuspendingTransactionId.get() == null) {
        return;
      }
      throw new IllegalStateException("Cannot access database on a different coroutine context inherited from a suspending transaction.");
    }
  }
  
  @Deprecated
  public void beginTransaction()
  {
    assertNotMainThread();
    SupportSQLiteDatabase localSupportSQLiteDatabase = mOpenHelper.getWritableDatabase();
    mInvalidationTracker.syncTriggers(localSupportSQLiteDatabase);
    localSupportSQLiteDatabase.beginTransaction();
  }
  
  @WorkerThread
  public abstract void clearAllTables();
  
  public void close()
  {
    if (isOpen())
    {
      ReentrantReadWriteLock.WriteLock localWriteLock = mCloseLock.writeLock();
      try
      {
        localWriteLock.lock();
        mInvalidationTracker.stopMultiInstanceInvalidation();
        mOpenHelper.close();
        return;
      }
      finally
      {
        localWriteLock.unlock();
      }
    }
  }
  
  public SupportSQLiteStatement compileStatement(@NonNull String paramString)
  {
    assertNotMainThread();
    assertNotSuspendingTransaction();
    return mOpenHelper.getWritableDatabase().compileStatement(paramString);
  }
  
  @NonNull
  protected abstract InvalidationTracker createInvalidationTracker();
  
  @NonNull
  protected abstract SupportSQLiteOpenHelper createOpenHelper(DatabaseConfiguration paramDatabaseConfiguration);
  
  @Deprecated
  public void endTransaction()
  {
    mOpenHelper.getWritableDatabase().endTransaction();
    if (!inTransaction()) {
      mInvalidationTracker.refreshVersionsAsync();
    }
  }
  
  @RestrictTo({androidx.annotation.RestrictTo.Scope.LIBRARY_GROUP})
  Map<String, Object> getBackingFieldMap()
  {
    return mBackingFieldMap;
  }
  
  Lock getCloseLock()
  {
    return mCloseLock.readLock();
  }
  
  @NonNull
  public InvalidationTracker getInvalidationTracker()
  {
    return mInvalidationTracker;
  }
  
  @NonNull
  public SupportSQLiteOpenHelper getOpenHelper()
  {
    return mOpenHelper;
  }
  
  @NonNull
  public Executor getQueryExecutor()
  {
    return mQueryExecutor;
  }
  
  @RestrictTo({androidx.annotation.RestrictTo.Scope.LIBRARY_GROUP})
  ThreadLocal<Integer> getSuspendingTransactionId()
  {
    return mSuspendingTransactionId;
  }
  
  @NonNull
  public Executor getTransactionExecutor()
  {
    return mTransactionExecutor;
  }
  
  public boolean inTransaction()
  {
    return mOpenHelper.getWritableDatabase().inTransaction();
  }
  
  @CallSuper
  public void init(@NonNull DatabaseConfiguration paramDatabaseConfiguration)
  {
    mOpenHelper = createOpenHelper(paramDatabaseConfiguration);
    int i = Build.VERSION.SDK_INT;
    boolean bool1 = false;
    boolean bool2 = false;
    if (i >= 16)
    {
      bool1 = bool2;
      if (journalMode == JournalMode.WRITE_AHEAD_LOGGING) {
        bool1 = true;
      }
      mOpenHelper.setWriteAheadLoggingEnabled(bool1);
    }
    mCallbacks = callbacks;
    mQueryExecutor = queryExecutor;
    mTransactionExecutor = new TransactionExecutor(transactionExecutor);
    mAllowMainThreadQueries = allowMainThreadQueries;
    mWriteAheadLoggingEnabled = bool1;
    if (multiInstanceInvalidation) {
      mInvalidationTracker.startMultiInstanceInvalidation(context, name);
    }
  }
  
  protected void internalInitInvalidationTracker(@NonNull SupportSQLiteDatabase paramSupportSQLiteDatabase)
  {
    mInvalidationTracker.internalInit(paramSupportSQLiteDatabase);
  }
  
  public boolean isOpen()
  {
    SupportSQLiteDatabase localSupportSQLiteDatabase = mDatabase;
    return (localSupportSQLiteDatabase != null) && (localSupportSQLiteDatabase.isOpen());
  }
  
  public Cursor query(SupportSQLiteQuery paramSupportSQLiteQuery)
  {
    assertNotMainThread();
    assertNotSuspendingTransaction();
    return mOpenHelper.getWritableDatabase().query(paramSupportSQLiteQuery);
  }
  
  public Cursor query(String paramString, @Nullable Object[] paramArrayOfObject)
  {
    return mOpenHelper.getWritableDatabase().query(new SimpleSQLiteQuery(paramString, paramArrayOfObject));
  }
  
  /* Error */
  public <V> V runInTransaction(@NonNull java.util.concurrent.Callable<V> paramCallable)
  {
    // Byte code:
    //   0: aload_0
    //   1: invokevirtual 286	androidx/room/RoomDatabase:beginTransaction	()V
    //   4: aload_1
    //   5: invokeinterface 291 1 0
    //   10: astore_1
    //   11: aload_0
    //   12: invokevirtual 294	androidx/room/RoomDatabase:setTransactionSuccessful	()V
    //   15: aload_0
    //   16: invokevirtual 295	androidx/room/RoomDatabase:endTransaction	()V
    //   19: aload_1
    //   20: areturn
    //   21: astore_1
    //   22: goto +17 -> 39
    //   25: astore_1
    //   26: aload_1
    //   27: invokestatic 301	androidx/room/util/SneakyThrow:reThrow	(Ljava/lang/Exception;)V
    //   30: aload_0
    //   31: invokevirtual 295	androidx/room/RoomDatabase:endTransaction	()V
    //   34: aconst_null
    //   35: areturn
    //   36: astore_1
    //   37: aload_1
    //   38: athrow
    //   39: aload_0
    //   40: invokevirtual 295	androidx/room/RoomDatabase:endTransaction	()V
    //   43: aload_1
    //   44: athrow
    // Local variable table:
    //   start	length	slot	name	signature
    //   0	45	0	this	RoomDatabase
    //   0	45	1	paramCallable	java.util.concurrent.Callable<V>
    // Exception table:
    //   from	to	target	type
    //   4	15	21	finally
    //   26	30	21	finally
    //   37	39	21	finally
    //   4	15	25	java/lang/Exception
    //   4	15	36	java/lang/RuntimeException
  }
  
  public void runInTransaction(@NonNull Runnable paramRunnable)
  {
    beginTransaction();
    try
    {
      paramRunnable.run();
      setTransactionSuccessful();
      return;
    }
    finally
    {
      endTransaction();
    }
  }
  
  @Deprecated
  public void setTransactionSuccessful()
  {
    mOpenHelper.getWritableDatabase().setTransactionSuccessful();
  }
  
  public static class Builder<T extends RoomDatabase>
  {
    private boolean mAllowDestructiveMigrationOnDowngrade;
    private boolean mAllowMainThreadQueries;
    private ArrayList<RoomDatabase.Callback> mCallbacks;
    private final Context mContext;
    private final Class<T> mDatabaseClass;
    private SupportSQLiteOpenHelper.Factory mFactory;
    private RoomDatabase.JournalMode mJournalMode;
    private final RoomDatabase.MigrationContainer mMigrationContainer;
    private Set<Integer> mMigrationStartAndEndVersions;
    private Set<Integer> mMigrationsNotRequiredFrom;
    private boolean mMultiInstanceInvalidation;
    private final String mName;
    private Executor mQueryExecutor;
    private boolean mRequireMigration;
    private Executor mTransactionExecutor;
    
    Builder(@NonNull Context paramContext, @NonNull Class<T> paramClass, @Nullable String paramString)
    {
      mContext = paramContext;
      mDatabaseClass = paramClass;
      mName = paramString;
      mJournalMode = RoomDatabase.JournalMode.AUTOMATIC;
      mRequireMigration = true;
      mMigrationContainer = new RoomDatabase.MigrationContainer();
    }
    
    @NonNull
    public Builder<T> addCallback(@NonNull RoomDatabase.Callback paramCallback)
    {
      if (mCallbacks == null) {
        mCallbacks = new ArrayList();
      }
      mCallbacks.add(paramCallback);
      return this;
    }
    
    @NonNull
    public Builder<T> addMigrations(@NonNull Migration... paramVarArgs)
    {
      if (mMigrationStartAndEndVersions == null) {
        mMigrationStartAndEndVersions = new HashSet();
      }
      int j = paramVarArgs.length;
      int i = 0;
      while (i < j)
      {
        Migration localMigration = paramVarArgs[i];
        mMigrationStartAndEndVersions.add(Integer.valueOf(startVersion));
        mMigrationStartAndEndVersions.add(Integer.valueOf(endVersion));
        i += 1;
      }
      mMigrationContainer.addMigrations(paramVarArgs);
      return this;
    }
    
    @NonNull
    public Builder<T> allowMainThreadQueries()
    {
      mAllowMainThreadQueries = true;
      return this;
    }
    
    @SuppressLint({"RestrictedApi"})
    @NonNull
    public T build()
    {
      if (mContext != null)
      {
        if (mDatabaseClass != null)
        {
          if ((mQueryExecutor == null) && (mTransactionExecutor == null))
          {
            localObject1 = ArchTaskExecutor.getIOThreadExecutor();
            mTransactionExecutor = ((Executor)localObject1);
            mQueryExecutor = ((Executor)localObject1);
          }
          else if ((mQueryExecutor != null) && (mTransactionExecutor == null))
          {
            mTransactionExecutor = mQueryExecutor;
          }
          else if ((mQueryExecutor == null) && (mTransactionExecutor != null))
          {
            mQueryExecutor = mTransactionExecutor;
          }
          if ((mMigrationStartAndEndVersions != null) && (mMigrationsNotRequiredFrom != null))
          {
            localObject2 = mMigrationStartAndEndVersions.iterator();
            while (((Iterator)localObject2).hasNext())
            {
              localObject1 = (Integer)((Iterator)localObject2).next();
              if (mMigrationsNotRequiredFrom.contains(localObject1))
              {
                localObject2 = new StringBuilder();
                ((StringBuilder)localObject2).append("Inconsistency detected. A Migration was supplied to addMigration(Migration... migrations) that has a start or end version equal to a start version supplied to fallbackToDestructiveMigrationFrom(int... startVersions). Start version: ");
                ((StringBuilder)localObject2).append(localObject1);
                throw new IllegalArgumentException(((StringBuilder)localObject2).toString());
              }
            }
          }
          if (mFactory == null) {
            mFactory = new FrameworkSQLiteOpenHelperFactory();
          }
          Object localObject1 = new DatabaseConfiguration(mContext, mName, mFactory, mMigrationContainer, mCallbacks, mAllowMainThreadQueries, mJournalMode.resolve(mContext), mQueryExecutor, mTransactionExecutor, mMultiInstanceInvalidation, mRequireMigration, mAllowDestructiveMigrationOnDowngrade, mMigrationsNotRequiredFrom);
          Object localObject2 = (RoomDatabase)Room.getGeneratedImplementation(mDatabaseClass, "_Impl");
          ((RoomDatabase)localObject2).init((DatabaseConfiguration)localObject1);
          return localObject2;
        }
        throw new IllegalArgumentException("Must provide an abstract class that extends RoomDatabase");
      }
      throw new IllegalArgumentException("Cannot provide null context for the database.");
    }
    
    @NonNull
    public Builder<T> enableMultiInstanceInvalidation()
    {
      boolean bool;
      if (mName != null) {
        bool = true;
      } else {
        bool = false;
      }
      mMultiInstanceInvalidation = bool;
      return this;
    }
    
    @NonNull
    public Builder<T> fallbackToDestructiveMigration()
    {
      mRequireMigration = false;
      mAllowDestructiveMigrationOnDowngrade = true;
      return this;
    }
    
    @NonNull
    public Builder<T> fallbackToDestructiveMigrationFrom(int... paramVarArgs)
    {
      if (mMigrationsNotRequiredFrom == null) {
        mMigrationsNotRequiredFrom = new HashSet(paramVarArgs.length);
      }
      int j = paramVarArgs.length;
      int i = 0;
      while (i < j)
      {
        int k = paramVarArgs[i];
        mMigrationsNotRequiredFrom.add(Integer.valueOf(k));
        i += 1;
      }
      return this;
    }
    
    @NonNull
    public Builder<T> fallbackToDestructiveMigrationOnDowngrade()
    {
      mRequireMigration = true;
      mAllowDestructiveMigrationOnDowngrade = true;
      return this;
    }
    
    @NonNull
    public Builder<T> openHelperFactory(@Nullable SupportSQLiteOpenHelper.Factory paramFactory)
    {
      mFactory = paramFactory;
      return this;
    }
    
    @NonNull
    public Builder<T> setJournalMode(@NonNull RoomDatabase.JournalMode paramJournalMode)
    {
      mJournalMode = paramJournalMode;
      return this;
    }
    
    @NonNull
    public Builder<T> setQueryExecutor(@NonNull Executor paramExecutor)
    {
      mQueryExecutor = paramExecutor;
      return this;
    }
    
    @NonNull
    public Builder<T> setTransactionExecutor(@NonNull Executor paramExecutor)
    {
      mTransactionExecutor = paramExecutor;
      return this;
    }
  }
  
  public static abstract class Callback
  {
    public Callback() {}
    
    public void onCreate(@NonNull SupportSQLiteDatabase paramSupportSQLiteDatabase) {}
    
    public void onOpen(@NonNull SupportSQLiteDatabase paramSupportSQLiteDatabase) {}
  }
  
  public static enum JournalMode
  {
    AUTOMATIC,  TRUNCATE,  WRITE_AHEAD_LOGGING;
    
    private JournalMode() {}
    
    @SuppressLint({"NewApi"})
    JournalMode resolve(Context paramContext)
    {
      if (this != AUTOMATIC) {
        return this;
      }
      if (Build.VERSION.SDK_INT >= 16)
      {
        paramContext = (ActivityManager)paramContext.getSystemService("activity");
        if ((paramContext != null) && (!ActivityManagerCompat.isLowRamDevice(paramContext))) {
          return WRITE_AHEAD_LOGGING;
        }
      }
      return TRUNCATE;
    }
  }
  
  public static class MigrationContainer
  {
    private SparseArrayCompat<SparseArrayCompat<Migration>> mMigrations = new SparseArrayCompat();
    
    public MigrationContainer() {}
    
    private void addMigration(Migration paramMigration)
    {
      int i = startVersion;
      int j = endVersion;
      Object localObject2 = (SparseArrayCompat)mMigrations.get(i);
      Object localObject1 = localObject2;
      if (localObject2 == null)
      {
        localObject1 = new SparseArrayCompat();
        mMigrations.put(i, localObject1);
      }
      localObject2 = (Migration)((SparseArrayCompat)localObject1).get(j);
      if (localObject2 != null)
      {
        StringBuilder localStringBuilder = new StringBuilder();
        localStringBuilder.append("Overriding migration ");
        localStringBuilder.append(localObject2);
        localStringBuilder.append(" with ");
        localStringBuilder.append(paramMigration);
        Log.w("ROOM", localStringBuilder.toString());
      }
      ((SparseArrayCompat)localObject1).append(j, paramMigration);
    }
    
    private List<Migration> findUpMigrationPath(List<Migration> paramList, boolean paramBoolean, int paramInt1, int paramInt2)
    {
      int i;
      int j;
      if (paramBoolean)
      {
        i = -1;
        j = paramInt1;
      }
      else
      {
        i = 1;
        j = paramInt1;
      }
      while (paramBoolean ? j < paramInt2 : j > paramInt2)
      {
        SparseArrayCompat localSparseArrayCompat = (SparseArrayCompat)mMigrations.get(j);
        if (localSparseArrayCompat == null) {
          return null;
        }
        int k = localSparseArrayCompat.size();
        int i1 = 0;
        if (paramBoolean)
        {
          paramInt1 = k - 1;
          k = -1;
        }
        else
        {
          paramInt1 = 0;
        }
        int m;
        int n;
        for (;;)
        {
          m = i1;
          n = j;
          if (paramInt1 == k) {
            break;
          }
          n = localSparseArrayCompat.keyAt(paramInt1);
          if (paramBoolean) {
            if ((n > paramInt2) || (n <= j)) {}
          }
          for (;;)
          {
            m = 1;
            break;
            do
            {
              m = 0;
              break;
            } while ((n < paramInt2) || (n >= j));
          }
          if (m != 0)
          {
            paramList.add(localSparseArrayCompat.valueAt(paramInt1));
            m = 1;
            break;
          }
          paramInt1 += i;
        }
        j = n;
        if (m == 0) {
          return null;
        }
      }
      return paramList;
    }
    
    public void addMigrations(@NonNull Migration... paramVarArgs)
    {
      int j = paramVarArgs.length;
      int i = 0;
      while (i < j)
      {
        addMigration(paramVarArgs[i]);
        i += 1;
      }
    }
    
    @Nullable
    public List<Migration> findMigrationPath(int paramInt1, int paramInt2)
    {
      if (paramInt1 == paramInt2) {
        return Collections.emptyList();
      }
      boolean bool;
      if (paramInt2 > paramInt1) {
        bool = true;
      } else {
        bool = false;
      }
      return findUpMigrationPath(new ArrayList(), bool, paramInt1, paramInt2);
    }
  }
}
