package com.google.android.gms.common.internal;

import android.accounts.Account;
import android.app.PendingIntent;
import android.content.ComponentName;
import android.content.Context;
import android.content.Intent;
import android.content.ServiceConnection;
import android.os.Bundle;
import android.os.DeadObjectException;
import android.os.Handler;
import android.os.IBinder;
import android.os.IInterface;
import android.os.Looper;
import android.os.Message;
import android.os.RemoteException;
import android.text.TextUtils;
import android.util.Log;
import androidx.annotation.BinderThread;
import androidx.annotation.CallSuper;
import androidx.annotation.NonNull;
import androidx.annotation.Nullable;
import androidx.annotation.WorkerThread;
import com.google.android.gms.common.ConnectionResult;
import com.google.android.gms.common.Feature;
import com.google.android.gms.common.GoogleApiAvailabilityLight;
import com.google.android.gms.common.annotation.KeepForSdk;
import com.google.android.gms.common.api.CommonStatusCodes;
import com.google.android.gms.common.api.Scope;
import com.google.android.gms.common.util.VisibleForTesting;
import com.google.android.gms.internal.common.zze;
import java.io.FileDescriptor;
import java.io.PrintWriter;
import java.text.SimpleDateFormat;
import java.util.ArrayList;
import java.util.Collection;
import java.util.Collections;
import java.util.Date;
import java.util.Locale;
import java.util.Set;
import java.util.concurrent.atomic.AtomicInteger;
import javax.annotation.concurrent.GuardedBy;

@KeepForSdk
public abstract class BaseGmsClient<T extends IInterface>
{
  @KeepForSdk
  public static final int CONNECT_STATE_CONNECTED = 4;
  @KeepForSdk
  public static final int CONNECT_STATE_DISCONNECTED = 1;
  @KeepForSdk
  public static final int CONNECT_STATE_DISCONNECTING = 5;
  @KeepForSdk
  public static final String DEFAULT_ACCOUNT = "<<default account>>";
  @KeepForSdk
  public static final String[] GOOGLE_PLUS_REQUIRED_FEATURES = { "service_esmobile", "service_googleme" };
  @KeepForSdk
  public static final String KEY_PENDING_INTENT = "pendingIntent";
  private static final Feature[] zzbt = new Feature[0];
  private final Context mContext;
  final Handler mHandler;
  private final Object mLock = new Object();
  private int zzbu;
  private long zzbv;
  private long zzbw;
  private int zzbx;
  private long zzby;
  @VisibleForTesting
  private zzh zzbz;
  private final Looper zzca;
  private final GmsClientSupervisor zzcb;
  private final GoogleApiAvailabilityLight zzcc;
  private final Object zzcd = new Object();
  @GuardedBy("mServiceBrokerLock")
  private IGmsServiceBroker zzce;
  @VisibleForTesting
  protected ConnectionProgressReportCallbacks zzcf;
  @GuardedBy("mLock")
  private T zzcg;
  private final ArrayList<zzc<?>> zzch = new ArrayList();
  @GuardedBy("mLock")
  private zze zzci;
  @GuardedBy("mLock")
  private int zzcj = 1;
  private final BaseConnectionCallbacks zzck;
  private final BaseOnConnectionFailedListener zzcl;
  private final int zzcm;
  private final String zzcn;
  private ConnectionResult zzco = null;
  private boolean zzcp = false;
  private volatile zzb zzcq = null;
  @VisibleForTesting
  protected AtomicInteger zzcr = new AtomicInteger(0);
  
  @KeepForSdk
  @VisibleForTesting
  protected BaseGmsClient(Context paramContext, Handler paramHandler, GmsClientSupervisor paramGmsClientSupervisor, GoogleApiAvailabilityLight paramGoogleApiAvailabilityLight, int paramInt, BaseConnectionCallbacks paramBaseConnectionCallbacks, BaseOnConnectionFailedListener paramBaseOnConnectionFailedListener)
  {
    mContext = ((Context)Preconditions.checkNotNull(paramContext, "Context must not be null"));
    mHandler = ((Handler)Preconditions.checkNotNull(paramHandler, "Handler must not be null"));
    zzca = paramHandler.getLooper();
    zzcb = ((GmsClientSupervisor)Preconditions.checkNotNull(paramGmsClientSupervisor, "Supervisor must not be null"));
    zzcc = ((GoogleApiAvailabilityLight)Preconditions.checkNotNull(paramGoogleApiAvailabilityLight, "API availability must not be null"));
    zzcm = paramInt;
    zzck = paramBaseConnectionCallbacks;
    zzcl = paramBaseOnConnectionFailedListener;
    zzcn = null;
  }
  
  @KeepForSdk
  protected BaseGmsClient(Context paramContext, Looper paramLooper, int paramInt, BaseConnectionCallbacks paramBaseConnectionCallbacks, BaseOnConnectionFailedListener paramBaseOnConnectionFailedListener, String paramString)
  {
    this(paramContext, paramLooper, GmsClientSupervisor.getInstance(paramContext), GoogleApiAvailabilityLight.getInstance(), paramInt, (BaseConnectionCallbacks)Preconditions.checkNotNull(paramBaseConnectionCallbacks), (BaseOnConnectionFailedListener)Preconditions.checkNotNull(paramBaseOnConnectionFailedListener), paramString);
  }
  
  @KeepForSdk
  @VisibleForTesting
  protected BaseGmsClient(Context paramContext, Looper paramLooper, GmsClientSupervisor paramGmsClientSupervisor, GoogleApiAvailabilityLight paramGoogleApiAvailabilityLight, int paramInt, BaseConnectionCallbacks paramBaseConnectionCallbacks, BaseOnConnectionFailedListener paramBaseOnConnectionFailedListener, String paramString)
  {
    mContext = ((Context)Preconditions.checkNotNull(paramContext, "Context must not be null"));
    zzca = ((Looper)Preconditions.checkNotNull(paramLooper, "Looper must not be null"));
    zzcb = ((GmsClientSupervisor)Preconditions.checkNotNull(paramGmsClientSupervisor, "Supervisor must not be null"));
    zzcc = ((GoogleApiAvailabilityLight)Preconditions.checkNotNull(paramGoogleApiAvailabilityLight, "API availability must not be null"));
    mHandler = new zzb(paramLooper);
    zzcm = paramInt;
    zzck = paramBaseConnectionCallbacks;
    zzcl = paramBaseOnConnectionFailedListener;
    zzcn = paramString;
  }
  
  private final void zza(int paramInt, T paramT)
  {
    int i;
    if (paramInt == 4) {
      i = 1;
    } else {
      i = 0;
    }
    int j;
    if (paramT != null) {
      j = 1;
    } else {
      j = 0;
    }
    boolean bool;
    if (i == j) {
      bool = true;
    } else {
      bool = false;
    }
    Preconditions.checkArgument(bool);
    for (;;)
    {
      synchronized (mLock)
      {
        zzcj = paramInt;
        zzcg = paramT;
        onSetConnectState(paramInt, paramT);
        switch (paramInt)
        {
        case 4: 
          onConnectedLocked(paramT);
          break;
        case 2: 
        case 3: 
          if ((zzci != null) && (zzbz != null))
          {
            paramT = zzbz.zzt();
            str1 = zzbz.getPackageName();
            localObject2 = new StringBuilder(String.valueOf(paramT).length() + 70 + String.valueOf(str1).length());
            ((StringBuilder)localObject2).append("Calling connect() while still connected, missing disconnect() for ");
            ((StringBuilder)localObject2).append(paramT);
            ((StringBuilder)localObject2).append(" on ");
            ((StringBuilder)localObject2).append(str1);
            Log.e("GmsClient", ((StringBuilder)localObject2).toString());
            zzcb.zza(zzbz.zzt(), zzbz.getPackageName(), zzbz.zzq(), zzci, zzj());
            zzcr.incrementAndGet();
          }
          zzci = new zze(zzcr.get());
          if ((zzcj == 3) && (getLocalStartServiceAction() != null)) {
            paramT = new zzh(getContext().getPackageName(), getLocalStartServiceAction(), true, 129);
          } else {
            paramT = new zzh(getStartServicePackage(), getStartServiceAction(), false, 129);
          }
          zzbz = paramT;
          paramT = zzcb;
          String str1 = zzbz.zzt();
          Object localObject2 = zzbz.getPackageName();
          paramInt = zzbz.zzq();
          zze localZze = zzci;
          String str2 = zzj();
          if (!paramT.zza(new GmsClientSupervisor.zza(str1, (String)localObject2, paramInt), localZze, str2))
          {
            paramT = zzbz.zzt();
            str1 = zzbz.getPackageName();
            localObject2 = new StringBuilder(String.valueOf(paramT).length() + 34 + String.valueOf(str1).length());
            ((StringBuilder)localObject2).append("unable to connect to service: ");
            ((StringBuilder)localObject2).append(paramT);
            ((StringBuilder)localObject2).append(" on ");
            ((StringBuilder)localObject2).append(str1);
            Log.e("GmsClient", ((StringBuilder)localObject2).toString());
            zza(16, null, zzcr.get());
          }
          break;
        case 1: 
          if (zzci != null)
          {
            zzcb.zza(zzbz.zzt(), zzbz.getPackageName(), zzbz.zzq(), zzci, zzj());
            zzci = null;
          }
          return;
        }
      }
    }
  }
  
  private final void zza(zzb paramZzb)
  {
    zzcq = paramZzb;
  }
  
  private final boolean zza(int paramInt1, int paramInt2, T paramT)
  {
    synchronized (mLock)
    {
      if (zzcj != paramInt1) {
        return false;
      }
      zza(paramInt2, paramT);
      return true;
    }
  }
  
  private final void zzb(int paramInt)
  {
    if (zzk())
    {
      paramInt = 5;
      zzcp = true;
    }
    else
    {
      paramInt = 4;
    }
    mHandler.sendMessage(mHandler.obtainMessage(paramInt, zzcr.get(), 16));
  }
  
  @Nullable
  private final String zzj()
  {
    if (zzcn == null) {
      return mContext.getClass().getName();
    }
    return zzcn;
  }
  
  private final boolean zzk()
  {
    for (;;)
    {
      synchronized (mLock)
      {
        if (zzcj == 3)
        {
          bool = true;
          return bool;
        }
      }
      boolean bool = false;
    }
  }
  
  private final boolean zzl()
  {
    if (zzcp) {
      return false;
    }
    if (TextUtils.isEmpty(getServiceDescriptor())) {
      return false;
    }
    if (TextUtils.isEmpty(getLocalStartServiceAction())) {
      return false;
    }
    try
    {
      Class.forName(getServiceDescriptor());
      return true;
    }
    catch (ClassNotFoundException localClassNotFoundException) {}
    return false;
  }
  
  @KeepForSdk
  public void checkAvailabilityAndConnect()
  {
    int i = zzcc.isGooglePlayServicesAvailable(mContext, getMinApkVersion());
    if (i != 0)
    {
      zza(1, null);
      triggerNotAvailable(new LegacyClientCallbackAdapter(), i, null);
      return;
    }
    connect(new LegacyClientCallbackAdapter());
  }
  
  @KeepForSdk
  protected final void checkConnected()
  {
    if (isConnected()) {
      return;
    }
    throw new IllegalStateException("Not connected. Call connect() and wait for onConnected() to be called.");
  }
  
  @KeepForSdk
  public void connect(@NonNull ConnectionProgressReportCallbacks paramConnectionProgressReportCallbacks)
  {
    zzcf = ((ConnectionProgressReportCallbacks)Preconditions.checkNotNull(paramConnectionProgressReportCallbacks, "Connection progress callbacks cannot be null."));
    zza(2, null);
  }
  
  @Nullable
  @KeepForSdk
  protected abstract T createServiceInterface(IBinder paramIBinder);
  
  @KeepForSdk
  public void disconnect()
  {
    zzcr.incrementAndGet();
    synchronized (zzch)
    {
      int j = zzch.size();
      int i = 0;
      while (i < j)
      {
        ((zzc)zzch.get(i)).removeListener();
        i += 1;
      }
      zzch.clear();
      synchronized (zzcd)
      {
        zzce = null;
        zza(1, null);
        return;
      }
    }
  }
  
  @KeepForSdk
  public void dump(String paramString, FileDescriptor paramFileDescriptor, PrintWriter paramPrintWriter, String[] arg4)
  {
    synchronized (mLock)
    {
      int i = zzcj;
      paramFileDescriptor = zzcg;
      synchronized (zzcd)
      {
        Object localObject = zzce;
        paramPrintWriter.append(paramString).append("mConnectState=");
        switch (i)
        {
        default: 
          paramPrintWriter.print("UNKNOWN");
          break;
        case 5: 
          paramPrintWriter.print("DISCONNECTING");
          break;
        case 4: 
          paramPrintWriter.print("CONNECTED");
          break;
        case 3: 
          paramPrintWriter.print("LOCAL_CONNECTING");
          break;
        case 2: 
          paramPrintWriter.print("REMOTE_CONNECTING");
          break;
        case 1: 
          paramPrintWriter.print("DISCONNECTED");
        }
        paramPrintWriter.append(" mService=");
        if (paramFileDescriptor == null) {
          paramPrintWriter.append("null");
        } else {
          paramPrintWriter.append(getServiceDescriptor()).append("@").append(Integer.toHexString(System.identityHashCode(paramFileDescriptor.asBinder())));
        }
        paramPrintWriter.append(" mServiceBroker=");
        if (localObject == null) {
          paramPrintWriter.println("null");
        } else {
          paramPrintWriter.append("IGmsServiceBroker@").println(Integer.toHexString(System.identityHashCode(((IGmsServiceBroker)localObject).asBinder())));
        }
        paramFileDescriptor = new SimpleDateFormat("yyyy-MM-dd HH:mm:ss.SSS", Locale.US);
        long l;
        StringBuilder localStringBuilder;
        if (zzbw > 0L)
        {
          ??? = paramPrintWriter.append(paramString).append("lastConnectedTime=");
          l = zzbw;
          localObject = paramFileDescriptor.format(new Date(zzbw));
          localStringBuilder = new StringBuilder(String.valueOf(localObject).length() + 21);
          localStringBuilder.append(l);
          localStringBuilder.append(" ");
          localStringBuilder.append((String)localObject);
          ???.println(localStringBuilder.toString());
        }
        if (zzbv > 0L)
        {
          paramPrintWriter.append(paramString).append("lastSuspendedCause=");
          switch (zzbu)
          {
          default: 
            paramPrintWriter.append(String.valueOf(zzbu));
            break;
          case 2: 
            paramPrintWriter.append("CAUSE_NETWORK_LOST");
            break;
          case 1: 
            paramPrintWriter.append("CAUSE_SERVICE_DISCONNECTED");
          }
          ??? = paramPrintWriter.append(" lastSuspendedTime=");
          l = zzbv;
          localObject = paramFileDescriptor.format(new Date(zzbv));
          localStringBuilder = new StringBuilder(String.valueOf(localObject).length() + 21);
          localStringBuilder.append(l);
          localStringBuilder.append(" ");
          localStringBuilder.append((String)localObject);
          ???.println(localStringBuilder.toString());
        }
        if (zzby > 0L)
        {
          paramPrintWriter.append(paramString).append("lastFailedStatus=").append(CommonStatusCodes.getStatusCodeString(zzbx));
          paramString = paramPrintWriter.append(" lastFailedTime=");
          l = zzby;
          paramFileDescriptor = paramFileDescriptor.format(new Date(zzby));
          paramPrintWriter = new StringBuilder(String.valueOf(paramFileDescriptor).length() + 21);
          paramPrintWriter.append(l);
          paramPrintWriter.append(" ");
          paramPrintWriter.append(paramFileDescriptor);
          paramString.println(paramPrintWriter.toString());
        }
        return;
      }
    }
  }
  
  @KeepForSdk
  protected boolean enableLocalFallback()
  {
    return false;
  }
  
  @KeepForSdk
  public Account getAccount()
  {
    return null;
  }
  
  @KeepForSdk
  public Feature[] getApiFeatures()
  {
    return zzbt;
  }
  
  @Nullable
  @KeepForSdk
  public final Feature[] getAvailableFeatures()
  {
    zzb localZzb = zzcq;
    if (localZzb == null) {
      return null;
    }
    return zzdb;
  }
  
  @KeepForSdk
  public Bundle getConnectionHint()
  {
    return null;
  }
  
  @KeepForSdk
  public final Context getContext()
  {
    return mContext;
  }
  
  @KeepForSdk
  public String getEndpointPackageName()
  {
    if ((isConnected()) && (zzbz != null)) {
      return zzbz.getPackageName();
    }
    throw new RuntimeException("Failed to connect when checking package");
  }
  
  @KeepForSdk
  protected Bundle getGetServiceRequestExtraArgs()
  {
    return new Bundle();
  }
  
  @Nullable
  @KeepForSdk
  protected String getLocalStartServiceAction()
  {
    return null;
  }
  
  @KeepForSdk
  public final Looper getLooper()
  {
    return zzca;
  }
  
  @KeepForSdk
  public int getMinApkVersion()
  {
    return GoogleApiAvailabilityLight.GOOGLE_PLAY_SERVICES_VERSION_CODE;
  }
  
  @WorkerThread
  @KeepForSdk
  public void getRemoteService(IAccountAccessor arg1, Set<Scope> paramSet)
  {
    Bundle localBundle = getGetServiceRequestExtraArgs();
    GetServiceRequest localGetServiceRequest = new GetServiceRequest(zzcm);
    zzy = mContext.getPackageName();
    zzdk = localBundle;
    if (paramSet != null) {
      zzdj = ((Scope[])paramSet.toArray(new Scope[paramSet.size()]));
    }
    if (requiresSignIn())
    {
      if (getAccount() != null) {
        paramSet = getAccount();
      } else {
        paramSet = new Account("<<default account>>", "com.google");
      }
      zzdl = paramSet;
      if (??? != null) {
        zzdi = ???.asBinder();
      }
    }
    else if (requiresAccount())
    {
      zzdl = getAccount();
    }
    zzdm = zzbt;
    zzdn = getApiFeatures();
    try
    {
      synchronized (zzcd)
      {
        if (zzce != null) {
          zzce.getService(new zzd(this, zzcr.get()), localGetServiceRequest);
        } else {
          Log.w("GmsClient", "mServiceBroker is null, client disconnected");
        }
        return;
      }
      return;
    }
    catch (RemoteException|RuntimeException ???)
    {
      Log.w("GmsClient", "IGmsServiceBroker.getService failed", ???);
      onPostInitHandler(8, null, null, zzcr.get());
      return;
    }
    catch (SecurityException ???)
    {
      throw ???;
    }
    catch (DeadObjectException ???)
    {
      Log.w("GmsClient", "IGmsServiceBroker.getService failed", ???);
      triggerConnectionSuspended(1);
    }
  }
  
  @KeepForSdk
  protected Set<Scope> getScopes()
  {
    return Collections.EMPTY_SET;
  }
  
  @KeepForSdk
  public final T getService()
    throws DeadObjectException
  {
    for (;;)
    {
      synchronized (mLock)
      {
        if (zzcj != 5)
        {
          checkConnected();
          if (zzcg != null)
          {
            bool = true;
            Preconditions.checkState(bool, "Client is connected but service is null");
            IInterface localIInterface = zzcg;
            return localIInterface;
          }
        }
        else
        {
          throw new DeadObjectException();
        }
      }
      boolean bool = false;
    }
  }
  
  @Nullable
  @KeepForSdk
  public IBinder getServiceBrokerBinder()
  {
    synchronized (zzcd)
    {
      if (zzce == null) {
        return null;
      }
      IBinder localIBinder = zzce.asBinder();
      return localIBinder;
    }
  }
  
  @NonNull
  @KeepForSdk
  protected abstract String getServiceDescriptor();
  
  @KeepForSdk
  public Intent getSignInIntent()
  {
    throw new UnsupportedOperationException("Not a sign in API");
  }
  
  @NonNull
  @KeepForSdk
  protected abstract String getStartServiceAction();
  
  @KeepForSdk
  protected String getStartServicePackage()
  {
    return "com.google.android.gms";
  }
  
  @KeepForSdk
  public boolean isConnected()
  {
    for (;;)
    {
      synchronized (mLock)
      {
        if (zzcj == 4)
        {
          bool = true;
          return bool;
        }
      }
      boolean bool = false;
    }
  }
  
  @KeepForSdk
  public boolean isConnecting()
  {
    for (;;)
    {
      synchronized (mLock)
      {
        if (zzcj == 2) {
          break label40;
        }
        if (zzcj == 3)
        {
          break label40;
          return bool;
        }
      }
      boolean bool = false;
      continue;
      label40:
      bool = true;
    }
  }
  
  @CallSuper
  @KeepForSdk
  protected void onConnectedLocked(@NonNull T paramT)
  {
    zzbw = System.currentTimeMillis();
  }
  
  @CallSuper
  @KeepForSdk
  protected void onConnectionFailed(ConnectionResult paramConnectionResult)
  {
    zzbx = paramConnectionResult.getErrorCode();
    zzby = System.currentTimeMillis();
  }
  
  @CallSuper
  @KeepForSdk
  protected void onConnectionSuspended(int paramInt)
  {
    zzbu = paramInt;
    zzbv = System.currentTimeMillis();
  }
  
  @KeepForSdk
  protected void onPostInitHandler(int paramInt1, IBinder paramIBinder, Bundle paramBundle, int paramInt2)
  {
    mHandler.sendMessage(mHandler.obtainMessage(1, paramInt2, -1, new zzf(paramInt1, paramIBinder, paramBundle)));
  }
  
  @KeepForSdk
  void onSetConnectState(int paramInt, T paramT) {}
  
  @KeepForSdk
  public void onUserSignOut(@NonNull SignOutCallbacks paramSignOutCallbacks)
  {
    paramSignOutCallbacks.onSignOutComplete();
  }
  
  @KeepForSdk
  public boolean providesSignIn()
  {
    return false;
  }
  
  @KeepForSdk
  public boolean requiresAccount()
  {
    return false;
  }
  
  @KeepForSdk
  public boolean requiresGooglePlayServices()
  {
    return true;
  }
  
  @KeepForSdk
  public boolean requiresSignIn()
  {
    return false;
  }
  
  @KeepForSdk
  public void triggerConnectionSuspended(int paramInt)
  {
    mHandler.sendMessage(mHandler.obtainMessage(6, zzcr.get(), paramInt));
  }
  
  @KeepForSdk
  @VisibleForTesting
  protected void triggerNotAvailable(@NonNull ConnectionProgressReportCallbacks paramConnectionProgressReportCallbacks, int paramInt, @Nullable PendingIntent paramPendingIntent)
  {
    zzcf = ((ConnectionProgressReportCallbacks)Preconditions.checkNotNull(paramConnectionProgressReportCallbacks, "Connection progress callbacks cannot be null."));
    mHandler.sendMessage(mHandler.obtainMessage(3, zzcr.get(), paramInt, paramPendingIntent));
  }
  
  protected final void zza(int paramInt1, @Nullable Bundle paramBundle, int paramInt2)
  {
    mHandler.sendMessage(mHandler.obtainMessage(7, paramInt2, -1, new zzg(paramInt1, null)));
  }
  
  @KeepForSdk
  public static abstract interface BaseConnectionCallbacks
  {
    @KeepForSdk
    public abstract void onConnected(@Nullable Bundle paramBundle);
    
    @KeepForSdk
    public abstract void onConnectionSuspended(int paramInt);
  }
  
  @KeepForSdk
  public static abstract interface BaseOnConnectionFailedListener
  {
    public abstract void onConnectionFailed(@NonNull ConnectionResult paramConnectionResult);
  }
  
  @KeepForSdk
  public static abstract interface ConnectionProgressReportCallbacks
  {
    @KeepForSdk
    public abstract void onReportServiceBinding(@NonNull ConnectionResult paramConnectionResult);
  }
  
  protected class LegacyClientCallbackAdapter
    implements BaseGmsClient.ConnectionProgressReportCallbacks
  {
    @KeepForSdk
    public LegacyClientCallbackAdapter() {}
    
    public void onReportServiceBinding(@NonNull ConnectionResult paramConnectionResult)
    {
      if (paramConnectionResult.isSuccess())
      {
        getRemoteService(null, getScopes());
        return;
      }
      if (BaseGmsClient.zzg(BaseGmsClient.this) != null) {
        BaseGmsClient.zzg(BaseGmsClient.this).onConnectionFailed(paramConnectionResult);
      }
    }
  }
  
  @KeepForSdk
  public static abstract interface SignOutCallbacks
  {
    @KeepForSdk
    public abstract void onSignOutComplete();
  }
  
  private abstract class zza
    extends BaseGmsClient.zzc<Boolean>
  {
    private final int statusCode;
    private final Bundle zzcs;
    
    @BinderThread
    protected zza(int paramInt, Bundle paramBundle)
    {
      super(Boolean.valueOf(true));
      statusCode = paramInt;
      zzcs = paramBundle;
    }
    
    protected abstract void zza(ConnectionResult paramConnectionResult);
    
    protected abstract boolean zzm();
    
    protected final void zzn() {}
  }
  
  final class zzb
    extends zze
  {
    public zzb(Looper paramLooper)
    {
      super();
    }
    
    private static void zza(Message paramMessage)
    {
      paramMessage = (BaseGmsClient.zzc)obj;
      paramMessage.zzn();
      paramMessage.unregister();
    }
    
    private static boolean zzb(Message paramMessage)
    {
      if ((what != 2) && (what != 1)) {
        return what == 7;
      }
      return true;
    }
    
    public final void handleMessage(Message paramMessage)
    {
      if (zzcr.get() != arg1)
      {
        if (zzb(paramMessage)) {
          zza(paramMessage);
        }
        return;
      }
      if (((what == 1) || (what == 7) || ((what == 4) && (!enableLocalFallback())) || (what == 5)) && (!isConnecting()))
      {
        zza(paramMessage);
        return;
      }
      int i = what;
      PendingIntent localPendingIntent = null;
      if (i == 4)
      {
        BaseGmsClient.zza(BaseGmsClient.this, new ConnectionResult(arg2));
        if ((BaseGmsClient.zzb(BaseGmsClient.this)) && (!BaseGmsClient.zzc(BaseGmsClient.this)))
        {
          BaseGmsClient.zza(BaseGmsClient.this, 3, null);
          return;
        }
        if (BaseGmsClient.zzd(BaseGmsClient.this) != null) {
          paramMessage = BaseGmsClient.zzd(BaseGmsClient.this);
        } else {
          paramMessage = new ConnectionResult(8);
        }
        zzcf.onReportServiceBinding(paramMessage);
        onConnectionFailed(paramMessage);
        return;
      }
      if (what == 5)
      {
        if (BaseGmsClient.zzd(BaseGmsClient.this) != null) {
          paramMessage = BaseGmsClient.zzd(BaseGmsClient.this);
        } else {
          paramMessage = new ConnectionResult(8);
        }
        zzcf.onReportServiceBinding(paramMessage);
        onConnectionFailed(paramMessage);
        return;
      }
      if (what == 3)
      {
        if ((obj instanceof PendingIntent)) {
          localPendingIntent = (PendingIntent)obj;
        }
        paramMessage = new ConnectionResult(arg2, localPendingIntent);
        zzcf.onReportServiceBinding(paramMessage);
        onConnectionFailed(paramMessage);
        return;
      }
      if (what == 6)
      {
        BaseGmsClient.zza(BaseGmsClient.this, 5, null);
        if (BaseGmsClient.zze(BaseGmsClient.this) != null) {
          BaseGmsClient.zze(BaseGmsClient.this).onConnectionSuspended(arg2);
        }
        onConnectionSuspended(arg2);
        BaseGmsClient.zza(BaseGmsClient.this, 5, 1, null);
        return;
      }
      if ((what == 2) && (!isConnected()))
      {
        zza(paramMessage);
        return;
      }
      if (zzb(paramMessage))
      {
        ((BaseGmsClient.zzc)obj).zzo();
        return;
      }
      i = what;
      paramMessage = new StringBuilder(45);
      paramMessage.append("Don't know how to handle message: ");
      paramMessage.append(i);
      Log.wtf("GmsClient", paramMessage.toString(), new Exception());
    }
  }
  
  protected abstract class zzc<TListener>
  {
    private TListener zzcu;
    private boolean zzcv;
    
    public zzc()
    {
      Object localObject;
      zzcu = localObject;
      zzcv = false;
    }
    
    public final void removeListener()
    {
      try
      {
        zzcu = null;
        return;
      }
      finally {}
    }
    
    public final void unregister()
    {
      removeListener();
      synchronized (BaseGmsClient.zzf(BaseGmsClient.this))
      {
        BaseGmsClient.zzf(BaseGmsClient.this).remove(this);
        return;
      }
    }
    
    protected abstract void zza(TListener paramTListener);
    
    protected abstract void zzn();
    
    /* Error */
    public final void zzo()
    {
      // Byte code:
      //   0: aload_0
      //   1: monitorenter
      //   2: aload_0
      //   3: getfield 24	com/google/android/gms/common/internal/BaseGmsClient$zzc:zzcu	Ljava/lang/Object;
      //   6: astore_1
      //   7: aload_0
      //   8: getfield 26	com/google/android/gms/common/internal/BaseGmsClient$zzc:zzcv	Z
      //   11: ifeq +56 -> 67
      //   14: aload_0
      //   15: invokestatic 55	java/lang/String:valueOf	(Ljava/lang/Object;)Ljava/lang/String;
      //   18: astore_2
      //   19: new 57	java/lang/StringBuilder
      //   22: dup
      //   23: aload_2
      //   24: invokestatic 55	java/lang/String:valueOf	(Ljava/lang/Object;)Ljava/lang/String;
      //   27: invokevirtual 61	java/lang/String:length	()I
      //   30: bipush 47
      //   32: iadd
      //   33: invokespecial 64	java/lang/StringBuilder:<init>	(I)V
      //   36: astore_3
      //   37: aload_3
      //   38: ldc 66
      //   40: invokevirtual 70	java/lang/StringBuilder:append	(Ljava/lang/String;)Ljava/lang/StringBuilder;
      //   43: pop
      //   44: aload_3
      //   45: aload_2
      //   46: invokevirtual 70	java/lang/StringBuilder:append	(Ljava/lang/String;)Ljava/lang/StringBuilder;
      //   49: pop
      //   50: aload_3
      //   51: ldc 72
      //   53: invokevirtual 70	java/lang/StringBuilder:append	(Ljava/lang/String;)Ljava/lang/StringBuilder;
      //   56: pop
      //   57: ldc 74
      //   59: aload_3
      //   60: invokevirtual 78	java/lang/StringBuilder:toString	()Ljava/lang/String;
      //   63: invokestatic 84	android/util/Log:w	(Ljava/lang/String;Ljava/lang/String;)I
      //   66: pop
      //   67: aload_0
      //   68: monitorexit
      //   69: aload_1
      //   70: ifnull +18 -> 88
      //   73: aload_0
      //   74: aload_1
      //   75: invokevirtual 86	com/google/android/gms/common/internal/BaseGmsClient$zzc:zza	(Ljava/lang/Object;)V
      //   78: goto +14 -> 92
      //   81: astore_1
      //   82: aload_0
      //   83: invokevirtual 88	com/google/android/gms/common/internal/BaseGmsClient$zzc:zzn	()V
      //   86: aload_1
      //   87: athrow
      //   88: aload_0
      //   89: invokevirtual 88	com/google/android/gms/common/internal/BaseGmsClient$zzc:zzn	()V
      //   92: aload_0
      //   93: monitorenter
      //   94: aload_0
      //   95: iconst_1
      //   96: putfield 26	com/google/android/gms/common/internal/BaseGmsClient$zzc:zzcv	Z
      //   99: aload_0
      //   100: monitorexit
      //   101: aload_0
      //   102: invokevirtual 90	com/google/android/gms/common/internal/BaseGmsClient$zzc:unregister	()V
      //   105: return
      //   106: astore_1
      //   107: aload_0
      //   108: monitorexit
      //   109: aload_1
      //   110: athrow
      //   111: astore_1
      //   112: aload_0
      //   113: monitorexit
      //   114: aload_1
      //   115: athrow
      // Local variable table:
      //   start	length	slot	name	signature
      //   0	116	0	this	zzc
      //   6	69	1	localObject1	Object
      //   81	6	1	localRuntimeException	RuntimeException
      //   106	4	1	localObject2	Object
      //   111	4	1	localObject3	Object
      //   18	28	2	str	String
      //   36	24	3	localStringBuilder	StringBuilder
      // Exception table:
      //   from	to	target	type
      //   73	78	81	java/lang/RuntimeException
      //   94	101	106	finally
      //   107	109	106	finally
      //   2	67	111	finally
      //   67	69	111	finally
      //   112	114	111	finally
    }
  }
  
  @VisibleForTesting
  public static final class zzd
    extends IGmsCallbacks.zza
  {
    private BaseGmsClient zzcw;
    private final int zzcx;
    
    public zzd(@NonNull BaseGmsClient paramBaseGmsClient, int paramInt)
    {
      zzcw = paramBaseGmsClient;
      zzcx = paramInt;
    }
    
    @BinderThread
    public final void onPostInitComplete(int paramInt, @NonNull IBinder paramIBinder, @Nullable Bundle paramBundle)
    {
      Preconditions.checkNotNull(zzcw, "onPostInitComplete can be called only once per call to getRemoteService");
      zzcw.onPostInitHandler(paramInt, paramIBinder, paramBundle, zzcx);
      zzcw = null;
    }
    
    @BinderThread
    public final void zza(int paramInt, @Nullable Bundle paramBundle)
    {
      Log.wtf("GmsClient", "received deprecated onAccountValidationComplete callback, ignoring", new Exception());
    }
    
    @BinderThread
    public final void zza(int paramInt, @NonNull IBinder paramIBinder, @NonNull zzb paramZzb)
    {
      Preconditions.checkNotNull(zzcw, "onPostInitCompleteWithConnectionInfo can be called only once per call togetRemoteService");
      Preconditions.checkNotNull(paramZzb);
      BaseGmsClient.zza(zzcw, paramZzb);
      onPostInitComplete(paramInt, paramIBinder, zzda);
    }
  }
  
  @VisibleForTesting
  public final class zze
    implements ServiceConnection
  {
    private final int zzcx;
    
    public zze(int paramInt)
    {
      zzcx = paramInt;
    }
    
    public final void onServiceConnected(ComponentName paramComponentName, IBinder paramIBinder)
    {
      if (paramIBinder == null)
      {
        BaseGmsClient.zza(BaseGmsClient.this, 16);
        return;
      }
      synchronized (BaseGmsClient.zza(BaseGmsClient.this))
      {
        BaseGmsClient localBaseGmsClient = BaseGmsClient.this;
        if (paramIBinder == null)
        {
          paramComponentName = null;
        }
        else
        {
          paramComponentName = paramIBinder.queryLocalInterface("com.google.android.gms.common.internal.IGmsServiceBroker");
          if ((paramComponentName != null) && ((paramComponentName instanceof IGmsServiceBroker))) {
            paramComponentName = (IGmsServiceBroker)paramComponentName;
          } else {
            paramComponentName = new IGmsServiceBroker.Stub.zza(paramIBinder);
          }
        }
        BaseGmsClient.zza(localBaseGmsClient, paramComponentName);
        zza(0, null, zzcx);
        return;
      }
    }
    
    public final void onServiceDisconnected(ComponentName arg1)
    {
      synchronized (BaseGmsClient.zza(BaseGmsClient.this))
      {
        BaseGmsClient.zza(BaseGmsClient.this, null);
        mHandler.sendMessage(mHandler.obtainMessage(6, zzcx, 1));
        return;
      }
    }
  }
  
  protected final class zzf
    extends BaseGmsClient.zza
  {
    private final IBinder zzcy;
    
    @BinderThread
    public zzf(int paramInt, IBinder paramIBinder, Bundle paramBundle)
    {
      super(paramInt, paramBundle);
      zzcy = paramIBinder;
    }
    
    protected final void zza(ConnectionResult paramConnectionResult)
    {
      if (BaseGmsClient.zzg(BaseGmsClient.this) != null) {
        BaseGmsClient.zzg(BaseGmsClient.this).onConnectionFailed(paramConnectionResult);
      }
      onConnectionFailed(paramConnectionResult);
    }
    
    protected final boolean zzm()
    {
      try
      {
        Object localObject = zzcy.getInterfaceDescriptor();
        if (!getServiceDescriptor().equals(localObject))
        {
          String str = getServiceDescriptor();
          StringBuilder localStringBuilder = new StringBuilder(String.valueOf(str).length() + 34 + String.valueOf(localObject).length());
          localStringBuilder.append("service descriptor mismatch: ");
          localStringBuilder.append(str);
          localStringBuilder.append(" vs. ");
          localStringBuilder.append((String)localObject);
          Log.e("GmsClient", localStringBuilder.toString());
          return false;
        }
        localObject = createServiceInterface(zzcy);
        if ((localObject != null) && ((BaseGmsClient.zza(BaseGmsClient.this, 2, 4, (IInterface)localObject)) || (BaseGmsClient.zza(BaseGmsClient.this, 3, 4, (IInterface)localObject))))
        {
          BaseGmsClient.zza(BaseGmsClient.this, null);
          localObject = getConnectionHint();
          if (BaseGmsClient.zze(BaseGmsClient.this) != null) {
            BaseGmsClient.zze(BaseGmsClient.this).onConnected((Bundle)localObject);
          }
          return true;
        }
        return false;
      }
      catch (RemoteException localRemoteException)
      {
        for (;;) {}
      }
      Log.w("GmsClient", "service probably died");
      return false;
    }
  }
  
  protected final class zzg
    extends BaseGmsClient.zza
  {
    @BinderThread
    public zzg(@Nullable int paramInt, Bundle paramBundle)
    {
      super(paramInt, null);
    }
    
    protected final void zza(ConnectionResult paramConnectionResult)
    {
      if ((enableLocalFallback()) && (BaseGmsClient.zzb(BaseGmsClient.this)))
      {
        BaseGmsClient.zza(BaseGmsClient.this, 16);
        return;
      }
      zzcf.onReportServiceBinding(paramConnectionResult);
      onConnectionFailed(paramConnectionResult);
    }
    
    protected final boolean zzm()
    {
      zzcf.onReportServiceBinding(ConnectionResult.RESULT_SUCCESS);
      return true;
    }
  }
}
