package com.google.android.gms.iid;

import android.content.Context;
import android.content.SharedPreferences;
import android.content.SharedPreferences.Editor;
import android.text.TextUtils;
import android.util.Base64;
import android.util.Log;
import androidx.annotation.Nullable;
import androidx.annotation.WorkerThread;
import androidx.core.content.ContextCompat;
import java.io.File;
import java.io.IOException;
import java.io.UnsupportedEncodingException;

final class zzn
{
  zzn() {}
  
  @Nullable
  private static zzo zzd(SharedPreferences paramSharedPreferences, String paramString)
    throws zzp
  {
    String str1 = paramSharedPreferences.getString(zzak.zzh(paramString, "|P|"), null);
    String str2 = paramSharedPreferences.getString(zzak.zzh(paramString, "|K|"), null);
    if (str1 != null)
    {
      if (str2 == null) {
        return null;
      }
      return new zzo(zzg(str1, str2), zze(paramSharedPreferences, paramString));
    }
    return null;
  }
  
  /* Error */
  @Nullable
  private static zzo zzd(File paramFile)
    throws zzp, IOException
  {
    // Byte code:
    //   0: new 53	java/io/FileInputStream
    //   3: dup
    //   4: aload_0
    //   5: invokespecial 56	java/io/FileInputStream:<init>	(Ljava/io/File;)V
    //   8: astore 4
    //   10: aconst_null
    //   11: astore_3
    //   12: aload_3
    //   13: astore_0
    //   14: new 58	java/util/Properties
    //   17: dup
    //   18: invokespecial 59	java/util/Properties:<init>	()V
    //   21: astore 5
    //   23: aload_3
    //   24: astore_0
    //   25: aload 5
    //   27: aload 4
    //   29: invokevirtual 63	java/util/Properties:load	(Ljava/io/InputStream;)V
    //   32: aload_3
    //   33: astore_0
    //   34: aload 5
    //   36: ldc 65
    //   38: invokevirtual 69	java/util/Properties:getProperty	(Ljava/lang/String;)Ljava/lang/String;
    //   41: astore 6
    //   43: aload_3
    //   44: astore_0
    //   45: aload 5
    //   47: ldc 71
    //   49: invokevirtual 69	java/util/Properties:getProperty	(Ljava/lang/String;)Ljava/lang/String;
    //   52: astore 7
    //   54: aload 6
    //   56: ifnull +70 -> 126
    //   59: aload 7
    //   61: ifnonnull +6 -> 67
    //   64: goto +62 -> 126
    //   67: aload_3
    //   68: astore_0
    //   69: aload 6
    //   71: aload 7
    //   73: invokestatic 35	com/google/android/gms/iid/zzn:zzg	(Ljava/lang/String;Ljava/lang/String;)Ljava/security/KeyPair;
    //   76: astore 6
    //   78: aload_3
    //   79: astore_0
    //   80: aload 5
    //   82: ldc 73
    //   84: invokevirtual 69	java/util/Properties:getProperty	(Ljava/lang/String;)Ljava/lang/String;
    //   87: invokestatic 79	java/lang/Long:parseLong	(Ljava/lang/String;)J
    //   90: lstore_1
    //   91: aload_3
    //   92: astore_0
    //   93: new 31	com/google/android/gms/iid/zzo
    //   96: dup
    //   97: aload 6
    //   99: lload_1
    //   100: invokespecial 42	com/google/android/gms/iid/zzo:<init>	(Ljava/security/KeyPair;J)V
    //   103: astore_3
    //   104: aconst_null
    //   105: aload 4
    //   107: invokestatic 82	com/google/android/gms/iid/zzn:zzd	(Ljava/lang/Throwable;Ljava/io/FileInputStream;)V
    //   110: aload_3
    //   111: areturn
    //   112: astore 5
    //   114: aload_3
    //   115: astore_0
    //   116: new 13	com/google/android/gms/iid/zzp
    //   119: dup
    //   120: aload 5
    //   122: invokespecial 85	com/google/android/gms/iid/zzp:<init>	(Ljava/lang/Exception;)V
    //   125: athrow
    //   126: aconst_null
    //   127: aload 4
    //   129: invokestatic 82	com/google/android/gms/iid/zzn:zzd	(Ljava/lang/Throwable;Ljava/io/FileInputStream;)V
    //   132: aconst_null
    //   133: areturn
    //   134: astore_3
    //   135: goto +8 -> 143
    //   138: astore_3
    //   139: aload_3
    //   140: astore_0
    //   141: aload_3
    //   142: athrow
    //   143: aload_0
    //   144: aload 4
    //   146: invokestatic 82	com/google/android/gms/iid/zzn:zzd	(Ljava/lang/Throwable;Ljava/io/FileInputStream;)V
    //   149: aload_3
    //   150: athrow
    // Local variable table:
    //   start	length	slot	name	signature
    //   0	151	0	paramFile	File
    //   90	10	1	l	long
    //   11	104	3	localZzo	zzo
    //   134	1	3	localObject1	Object
    //   138	12	3	localThrowable	Throwable
    //   8	137	4	localFileInputStream	java.io.FileInputStream
    //   21	60	5	localProperties	java.util.Properties
    //   112	9	5	localNumberFormatException	NumberFormatException
    //   41	57	6	localObject2	Object
    //   52	20	7	str	String
    // Exception table:
    //   from	to	target	type
    //   80	91	112	java/lang/NumberFormatException
    //   14	23	134	finally
    //   25	32	134	finally
    //   34	43	134	finally
    //   45	54	134	finally
    //   69	78	134	finally
    //   80	91	134	finally
    //   93	104	134	finally
    //   116	126	134	finally
    //   141	143	134	finally
    //   14	23	138	java/lang/Throwable
    //   25	32	138	java/lang/Throwable
    //   34	43	138	java/lang/Throwable
    //   45	54	138	java/lang/Throwable
    //   69	78	138	java/lang/Throwable
    //   80	91	138	java/lang/Throwable
    //   93	104	138	java/lang/Throwable
    //   116	126	138	java/lang/Throwable
  }
  
  /* Error */
  private static void zzd(Context paramContext, String paramString, zzo paramZzo)
  {
    // Byte code:
    //   0: ldc 88
    //   2: iconst_3
    //   3: invokestatic 94	android/util/Log:isLoggable	(Ljava/lang/String;I)Z
    //   6: ifeq +11 -> 17
    //   9: ldc 88
    //   11: ldc 96
    //   13: invokestatic 100	android/util/Log:d	(Ljava/lang/String;Ljava/lang/String;)I
    //   16: pop
    //   17: aload_0
    //   18: aload_1
    //   19: invokestatic 104	com/google/android/gms/iid/zzn:zzj	(Landroid/content/Context;Ljava/lang/String;)Ljava/io/File;
    //   22: astore_0
    //   23: aload_0
    //   24: invokevirtual 110	java/io/File:createNewFile	()Z
    //   27: pop
    //   28: new 58	java/util/Properties
    //   31: dup
    //   32: invokespecial 59	java/util/Properties:<init>	()V
    //   35: astore_1
    //   36: aload_1
    //   37: ldc 65
    //   39: aload_2
    //   40: invokestatic 113	com/google/android/gms/iid/zzo:zzd	(Lcom/google/android/gms/iid/zzo;)Ljava/lang/String;
    //   43: invokevirtual 117	java/util/Properties:setProperty	(Ljava/lang/String;Ljava/lang/String;)Ljava/lang/Object;
    //   46: pop
    //   47: aload_1
    //   48: ldc 71
    //   50: aload_2
    //   51: invokestatic 119	com/google/android/gms/iid/zzo:zze	(Lcom/google/android/gms/iid/zzo;)Ljava/lang/String;
    //   54: invokevirtual 117	java/util/Properties:setProperty	(Ljava/lang/String;Ljava/lang/String;)Ljava/lang/Object;
    //   57: pop
    //   58: aload_1
    //   59: ldc 73
    //   61: aload_2
    //   62: invokestatic 123	com/google/android/gms/iid/zzo:zzf	(Lcom/google/android/gms/iid/zzo;)J
    //   65: invokestatic 129	java/lang/String:valueOf	(J)Ljava/lang/String;
    //   68: invokevirtual 117	java/util/Properties:setProperty	(Ljava/lang/String;Ljava/lang/String;)Ljava/lang/Object;
    //   71: pop
    //   72: new 131	java/io/FileOutputStream
    //   75: dup
    //   76: aload_0
    //   77: invokespecial 132	java/io/FileOutputStream:<init>	(Ljava/io/File;)V
    //   80: astore_2
    //   81: aconst_null
    //   82: astore_0
    //   83: aload_1
    //   84: aload_2
    //   85: aconst_null
    //   86: invokevirtual 136	java/util/Properties:store	(Ljava/io/OutputStream;Ljava/lang/String;)V
    //   89: aconst_null
    //   90: aload_2
    //   91: invokestatic 139	com/google/android/gms/iid/zzn:zzd	(Ljava/lang/Throwable;Ljava/io/FileOutputStream;)V
    //   94: return
    //   95: astore_1
    //   96: goto +8 -> 104
    //   99: astore_1
    //   100: aload_1
    //   101: astore_0
    //   102: aload_1
    //   103: athrow
    //   104: aload_0
    //   105: aload_2
    //   106: invokestatic 139	com/google/android/gms/iid/zzn:zzd	(Ljava/lang/Throwable;Ljava/io/FileOutputStream;)V
    //   109: aload_1
    //   110: athrow
    //   111: astore_0
    //   112: aload_0
    //   113: invokestatic 142	java/lang/String:valueOf	(Ljava/lang/Object;)Ljava/lang/String;
    //   116: astore_0
    //   117: new 144	java/lang/StringBuilder
    //   120: dup
    //   121: aload_0
    //   122: invokestatic 142	java/lang/String:valueOf	(Ljava/lang/Object;)Ljava/lang/String;
    //   125: invokevirtual 148	java/lang/String:length	()I
    //   128: bipush 21
    //   130: iadd
    //   131: invokespecial 151	java/lang/StringBuilder:<init>	(I)V
    //   134: astore_1
    //   135: aload_1
    //   136: ldc -103
    //   138: invokevirtual 157	java/lang/StringBuilder:append	(Ljava/lang/String;)Ljava/lang/StringBuilder;
    //   141: pop
    //   142: aload_1
    //   143: aload_0
    //   144: invokevirtual 157	java/lang/StringBuilder:append	(Ljava/lang/String;)Ljava/lang/StringBuilder;
    //   147: pop
    //   148: ldc 88
    //   150: aload_1
    //   151: invokevirtual 161	java/lang/StringBuilder:toString	()Ljava/lang/String;
    //   154: invokestatic 164	android/util/Log:w	(Ljava/lang/String;Ljava/lang/String;)I
    //   157: pop
    //   158: return
    // Local variable table:
    //   start	length	slot	name	signature
    //   0	159	0	paramContext	Context
    //   0	159	1	paramString	String
    //   0	159	2	paramZzo	zzo
    // Exception table:
    //   from	to	target	type
    //   83	89	95	finally
    //   102	104	95	finally
    //   83	89	99	java/lang/Throwable
    //   0	17	111	java/io/IOException
    //   17	81	111	java/io/IOException
    //   89	94	111	java/io/IOException
    //   104	111	111	java/io/IOException
  }
  
  private static long zze(SharedPreferences paramSharedPreferences, String paramString)
  {
    paramSharedPreferences = paramSharedPreferences.getString(zzak.zzh(paramString, "cre"), null);
    if (paramSharedPreferences != null) {}
    try
    {
      long l = Long.parseLong(paramSharedPreferences);
      return l;
    }
    catch (NumberFormatException paramSharedPreferences)
    {
      for (;;) {}
    }
    return 0L;
  }
  
  private final void zze(Context paramContext, String paramString, zzo paramZzo)
  {
    paramContext = paramContext.getSharedPreferences("com.google.android.gms.appid", 0);
    try
    {
      boolean bool = paramZzo.equals(zzd(paramContext, paramString));
      if (bool) {
        return;
      }
    }
    catch (zzp localZzp)
    {
      for (;;) {}
    }
    if (Log.isLoggable("InstanceID", 3)) {
      Log.d("InstanceID", "Writing key to shared preferences");
    }
    paramContext = paramContext.edit();
    paramContext.putString(zzak.zzh(paramString, "|P|"), zzo.zzd(paramZzo));
    paramContext.putString(zzak.zzh(paramString, "|K|"), zzo.zze(paramZzo));
    paramContext.putString(zzak.zzh(paramString, "cre"), String.valueOf(zzo.zzf(paramZzo)));
    paramContext.commit();
  }
  
  /* Error */
  private static java.security.KeyPair zzg(String paramString1, String paramString2)
    throws zzp
  {
    // Byte code:
    //   0: aload_0
    //   1: bipush 8
    //   3: invokestatic 214	android/util/Base64:decode	(Ljava/lang/String;I)[B
    //   6: astore_0
    //   7: aload_1
    //   8: bipush 8
    //   10: invokestatic 214	android/util/Base64:decode	(Ljava/lang/String;I)[B
    //   13: astore_1
    //   14: ldc -40
    //   16: invokestatic 222	java/security/KeyFactory:getInstance	(Ljava/lang/String;)Ljava/security/KeyFactory;
    //   19: astore_2
    //   20: new 224	java/security/KeyPair
    //   23: dup
    //   24: aload_2
    //   25: new 226	java/security/spec/X509EncodedKeySpec
    //   28: dup
    //   29: aload_0
    //   30: invokespecial 229	java/security/spec/X509EncodedKeySpec:<init>	([B)V
    //   33: invokevirtual 233	java/security/KeyFactory:generatePublic	(Ljava/security/spec/KeySpec;)Ljava/security/PublicKey;
    //   36: aload_2
    //   37: new 235	java/security/spec/PKCS8EncodedKeySpec
    //   40: dup
    //   41: aload_1
    //   42: invokespecial 236	java/security/spec/PKCS8EncodedKeySpec:<init>	([B)V
    //   45: invokevirtual 240	java/security/KeyFactory:generatePrivate	(Ljava/security/spec/KeySpec;)Ljava/security/PrivateKey;
    //   48: invokespecial 243	java/security/KeyPair:<init>	(Ljava/security/PublicKey;Ljava/security/PrivateKey;)V
    //   51: astore_0
    //   52: aload_0
    //   53: areturn
    //   54: astore_0
    //   55: aload_0
    //   56: invokestatic 142	java/lang/String:valueOf	(Ljava/lang/Object;)Ljava/lang/String;
    //   59: astore_1
    //   60: new 144	java/lang/StringBuilder
    //   63: dup
    //   64: aload_1
    //   65: invokestatic 142	java/lang/String:valueOf	(Ljava/lang/Object;)Ljava/lang/String;
    //   68: invokevirtual 148	java/lang/String:length	()I
    //   71: bipush 19
    //   73: iadd
    //   74: invokespecial 151	java/lang/StringBuilder:<init>	(I)V
    //   77: astore_2
    //   78: aload_2
    //   79: ldc -11
    //   81: invokevirtual 157	java/lang/StringBuilder:append	(Ljava/lang/String;)Ljava/lang/StringBuilder;
    //   84: pop
    //   85: aload_2
    //   86: aload_1
    //   87: invokevirtual 157	java/lang/StringBuilder:append	(Ljava/lang/String;)Ljava/lang/StringBuilder;
    //   90: pop
    //   91: ldc 88
    //   93: aload_2
    //   94: invokevirtual 161	java/lang/StringBuilder:toString	()Ljava/lang/String;
    //   97: invokestatic 164	android/util/Log:w	(Ljava/lang/String;Ljava/lang/String;)I
    //   100: pop
    //   101: new 13	com/google/android/gms/iid/zzp
    //   104: dup
    //   105: aload_0
    //   106: invokespecial 85	com/google/android/gms/iid/zzp:<init>	(Ljava/lang/Exception;)V
    //   109: athrow
    //   110: astore_0
    //   111: new 13	com/google/android/gms/iid/zzp
    //   114: dup
    //   115: aload_0
    //   116: invokespecial 85	com/google/android/gms/iid/zzp:<init>	(Ljava/lang/Exception;)V
    //   119: athrow
    // Local variable table:
    //   start	length	slot	name	signature
    //   0	120	0	paramString1	String
    //   0	120	1	paramString2	String
    //   19	75	2	localObject	Object
    // Exception table:
    //   from	to	target	type
    //   14	52	54	java/security/spec/InvalidKeySpecException
    //   14	52	54	java/security/NoSuchAlgorithmException
    //   0	14	110	java/lang/IllegalArgumentException
  }
  
  static void zzg(Context paramContext, String paramString)
  {
    paramContext = zzj(paramContext, paramString);
    if (paramContext.exists()) {
      paramContext.delete();
    }
  }
  
  @Nullable
  private final zzo zzh(Context paramContext, String paramString)
    throws zzp
  {
    try
    {
      zzo localZzo1 = zzi(paramContext, paramString);
      if (localZzo1 != null)
      {
        zze(paramContext, paramString, localZzo1);
        return localZzo1;
      }
      localZzo1 = null;
    }
    catch (zzp localZzp1) {}
    try
    {
      zzo localZzo2 = zzd(paramContext.getSharedPreferences("com.google.android.gms.appid", 0), paramString);
      if (localZzo2 != null)
      {
        zzd(paramContext, paramString, localZzo2);
        return localZzo2;
      }
    }
    catch (zzp localZzp2)
    {
      if (localZzp2 == null) {
        return null;
      }
      throw localZzp2;
    }
  }
  
  @Nullable
  private final zzo zzi(Context paramContext, String paramString)
    throws zzp
  {
    paramContext = zzj(paramContext, paramString);
    if (!paramContext.exists()) {
      return null;
    }
    try
    {
      paramString = zzd(paramContext);
      return paramString;
    }
    catch (IOException paramString)
    {
      StringBuilder localStringBuilder;
      if (Log.isLoggable("InstanceID", 3))
      {
        paramString = String.valueOf(paramString);
        localStringBuilder = new StringBuilder(String.valueOf(paramString).length() + 40);
        localStringBuilder.append("Failed to read key from file, retrying: ");
        localStringBuilder.append(paramString);
        Log.d("InstanceID", localStringBuilder.toString());
      }
      try
      {
        paramContext = zzd(paramContext);
        return paramContext;
      }
      catch (IOException paramContext)
      {
        paramString = String.valueOf(paramContext);
        localStringBuilder = new StringBuilder(String.valueOf(paramString).length() + 45);
        localStringBuilder.append("IID file exists, but failed to read from it: ");
        localStringBuilder.append(paramString);
        Log.w("InstanceID", localStringBuilder.toString());
        throw new zzp(paramContext);
      }
    }
  }
  
  static void zzi(Context paramContext)
  {
    paramContext = zzj(paramContext).listFiles();
    int j = paramContext.length;
    int i = 0;
    while (i < j)
    {
      Object localObject = paramContext[i];
      if (localObject.getName().startsWith("com.google.InstanceId")) {
        localObject.delete();
      }
      i += 1;
    }
  }
  
  private static File zzj(Context paramContext)
  {
    File localFile = ContextCompat.getNoBackupFilesDir(paramContext);
    if ((localFile != null) && (localFile.isDirectory())) {
      return localFile;
    }
    Log.w("InstanceID", "noBackupFilesDir doesn't exist, using regular files directory instead");
    return paramContext.getFilesDir();
  }
  
  private static File zzj(Context paramContext, String paramString)
  {
    if (TextUtils.isEmpty(paramString)) {
      paramString = "com.google.InstanceId.properties";
    }
    try
    {
      paramString = Base64.encodeToString(paramString.getBytes("UTF-8"), 11);
      StringBuilder localStringBuilder = new StringBuilder(String.valueOf(paramString).length() + 33);
      localStringBuilder.append("com.google.InstanceId_");
      localStringBuilder.append(paramString);
      localStringBuilder.append(".properties");
      paramString = localStringBuilder.toString();
      return new File(zzj(paramContext), paramString);
    }
    catch (UnsupportedEncodingException paramContext)
    {
      throw new AssertionError(paramContext);
    }
  }
  
  @WorkerThread
  final zzo zze(Context paramContext, String paramString)
    throws zzp
  {
    zzo localZzo = zzh(paramContext, paramString);
    if (localZzo != null) {
      return localZzo;
    }
    return zzf(paramContext, paramString);
  }
  
  @WorkerThread
  final zzo zzf(Context paramContext, String paramString)
  {
    zzo localZzo1 = new zzo(zzd.zzl(), System.currentTimeMillis());
    try
    {
      zzo localZzo2 = zzh(paramContext, paramString);
      if (localZzo2 != null)
      {
        if (Log.isLoggable("InstanceID", 3)) {
          Log.d("InstanceID", "Loaded key after generating new one, using loaded one");
        }
        return localZzo2;
      }
    }
    catch (zzp localZzp)
    {
      for (;;) {}
    }
    if (Log.isLoggable("InstanceID", 3)) {
      Log.d("InstanceID", "Generated new key");
    }
    zzd(paramContext, paramString, localZzo1);
    zze(paramContext, paramString, localZzo1);
    return localZzo1;
  }
}
