package ai.api.util;

import java.io.IOException;
import java.io.InputStream;
import java.io.InputStreamReader;
import java.io.OutputStream;
import java.io.Reader;
import java.io.StringWriter;
import java.io.Writer;
import java.nio.charset.Charset;

public class IOUtils
{
  private static final int DEFAULT_BUFFER_SIZE = 4096;
  private static final String DEFAULT_CHARSET = "UTF-8";
  
  public IOUtils() {}
  
  private static long copy(Reader paramReader, Writer paramWriter)
    throws IOException
  {
    return copy(paramReader, paramWriter, new char['?']);
  }
  
  private static long copy(Reader paramReader, Writer paramWriter, char[] paramArrayOfChar)
    throws IOException
  {
    long l = 0L;
    for (int i = paramReader.read(paramArrayOfChar); i > 0; i = paramReader.read(paramArrayOfChar))
    {
      paramWriter.write(paramArrayOfChar, 0, i);
      l += i;
    }
    return l;
  }
  
  public static String readAll(InputStream paramInputStream)
    throws IOException
  {
    return readAll(paramInputStream, "UTF-8");
  }
  
  /* Error */
  public static String readAll(InputStream paramInputStream, String paramString)
    throws IOException
  {
    // Byte code:
    //   0: new 49	java/io/InputStreamReader
    //   3: dup
    //   4: aload_0
    //   5: aload_1
    //   6: invokespecial 52	java/io/InputStreamReader:<init>	(Ljava/io/InputStream;Ljava/lang/String;)V
    //   9: astore_2
    //   10: aload_2
    //   11: invokestatic 55	ai/api/util/IOUtils:readAll	(Ljava/io/InputStreamReader;)Ljava/lang/String;
    //   14: astore_0
    //   15: aload_2
    //   16: invokevirtual 58	java/io/InputStreamReader:close	()V
    //   19: aload_0
    //   20: areturn
    //   21: astore_0
    //   22: aconst_null
    //   23: astore_1
    //   24: goto +7 -> 31
    //   27: astore_1
    //   28: aload_1
    //   29: athrow
    //   30: astore_0
    //   31: aload_1
    //   32: ifnull +19 -> 51
    //   35: aload_2
    //   36: invokevirtual 58	java/io/InputStreamReader:close	()V
    //   39: goto +16 -> 55
    //   42: astore_2
    //   43: aload_1
    //   44: aload_2
    //   45: invokevirtual 62	java/lang/Throwable:addSuppressed	(Ljava/lang/Throwable;)V
    //   48: goto +7 -> 55
    //   51: aload_2
    //   52: invokevirtual 58	java/io/InputStreamReader:close	()V
    //   55: aload_0
    //   56: athrow
    // Local variable table:
    //   start	length	slot	name	signature
    //   0	57	0	paramInputStream	InputStream
    //   0	57	1	paramString	String
    //   9	27	2	localInputStreamReader	InputStreamReader
    //   42	10	2	localThrowable	Throwable
    // Exception table:
    //   from	to	target	type
    //   10	15	21	finally
    //   10	15	27	java/lang/Throwable
    //   28	30	30	finally
    //   35	39	42	java/lang/Throwable
  }
  
  public static String readAll(InputStream paramInputStream, Charset paramCharset)
    throws IOException
  {
    return readAll(paramInputStream, paramCharset.name());
  }
  
  public static String readAll(InputStreamReader paramInputStreamReader)
    throws IOException
  {
    StringWriter localStringWriter = new StringWriter();
    copy(paramInputStreamReader, localStringWriter);
    return localStringWriter.toString();
  }
  
  public static void writeAll(String paramString, OutputStream paramOutputStream)
    throws IOException
  {
    writeAll(paramString, paramOutputStream, "UTF-8");
  }
  
  public static void writeAll(String paramString1, OutputStream paramOutputStream, String paramString2)
    throws IOException
  {
    if ((paramString1 != null) && (paramString1.length() > 0)) {
      paramOutputStream.write(paramString1.getBytes(paramString2));
    }
  }
  
  public static void writeAll(String paramString, OutputStream paramOutputStream, Charset paramCharset)
    throws IOException
  {
    writeAll(paramString, paramOutputStream, paramCharset.name());
  }
}
